easylogger/InitLogger.py
easylogger/__init__.py
easyredis/__init__.py
easyredis/listeningKit.py
easyredis/redisApi.py
easyutility/__init__.py
easyutility/stringUtils.py
easyutility/timeUtils.py
prologger/InitLogger.py
prologger/__init__.py
proredis/__init__.py
proredis/listeningKit.py
proredis/redisApi.py
proutility/__init__.py
proutility/stringUtils.py
proutility/timeUtils.py
tradecenter/CancelOrderByPrice.py
tradecenter/CancelOrderByTime.py
tradecenter/OrderManagerCenter.py
tradecenter/ResendOrderByRtnOrder.py
tradecenter/__init__.py
prologger-0.1.1.dist-info/METADATA
prologger-0.1.1.dist-info/WHEEL
prologger-0.1.1.dist-info/top_level.txt
prologger-0.1.1.dist-info/RECORD
