Metadata-Version: 2.1
Name: prologger
Version: 0.1.1
Summary: logger more easy ~
Home-page: http://your.package.home.page
Author: yuslience
Author-email: yuslience@163.com
License: UNKNOWN
Platform: UNKNOWN
Classifier: Development Status :: 3 - Alpha
Classifier: Intended Audience :: Developers
Classifier: License :: OSI Approved :: MIT License
Classifier: Programming Language :: Python :: 3.6
Requires-Python: >=3.6
Requires-Dist: loguru
